<?xml version="1.0" encoding="UTF-8"?>
<sv:node sv:name="samplepage" xmlns:sv="http://www.jcp.org/jcr/sv/1.0" xmlns:xsi="http://www.w3.org/2001/XMLSchema-instance">
  <sv:property sv:name="jcr:primaryType" sv:type="Name">
    <sv:value>mgnl:page</sv:value>
  </sv:property>
  <sv:property sv:name="jcr:mixinTypes" sv:type="Name" sv:multiple="true">
    <sv:value>mix:lockable</sv:value>
  </sv:property>
  <sv:property sv:name="jcr:uuid" sv:type="String">
    <sv:value>a3bbf72d-ac0e-4ba1-b4e8-2660178239db</sv:value>
  </sv:property>
  <sv:property sv:name="body" sv:type="String">
    <sv:value>&lt;p&gt;And here's the &lt;strong&gt;body&lt;/strong&gt;&amp;nbsp;&lt;/p&gt;</sv:value>
  </sv:property>
  <sv:property sv:name="jcr:createdBy" sv:type="String">
    <sv:value>admin</sv:value>
  </sv:property>
  <sv:property sv:name="title" sv:type="String">
    <sv:value>This is the title</sv:value>
  </sv:property>
  <sv:node sv:name="MetaData">
    <sv:property sv:name="jcr:primaryType" sv:type="Name">
      <sv:value>mgnl:metaData</sv:value>
    </sv:property>
    <sv:property sv:name="jcr:createdBy" sv:type="String">
      <sv:value>admin</sv:value>
    </sv:property>
    <sv:property sv:name="mgnl:authorid" sv:type="String">
      <sv:value>superuser</sv:value>
    </sv:property>
    <sv:property sv:name="mgnl:creationdate" sv:type="Date">
      <sv:value>2012-06-29T17:58:50.631+02:00</sv:value>
    </sv:property>
    <sv:property sv:name="mgnl:lastmodified" sv:type="Date">
      <sv:value>2012-06-29T18:22:06.664+02:00</sv:value>
    </sv:property>
    <sv:property sv:name="mgnl:template" sv:type="String">
      <sv:value>blossomModuleSample:pages/sampleTemplate</sv:value>
    </sv:property>
  </sv:node>
  <sv:node sv:name="left">
    <sv:property sv:name="jcr:primaryType" sv:type="Name">
      <sv:value>mgnl:area</sv:value>
    </sv:property>
    <sv:property sv:name="jcr:uuid" sv:type="String">
      <sv:value>a6ded0a2-1a40-49b5-b935-f4545b21c0c7</sv:value>
    </sv:property>
    <sv:property sv:name="jcr:createdBy" sv:type="String">
      <sv:value>admin</sv:value>
    </sv:property>
    <sv:node sv:name="MetaData">
      <sv:property sv:name="jcr:primaryType" sv:type="Name">
        <sv:value>mgnl:metaData</sv:value>
      </sv:property>
      <sv:property sv:name="jcr:createdBy" sv:type="String">
        <sv:value>admin</sv:value>
      </sv:property>
      <sv:property sv:name="mgnl:authorid" sv:type="String">
        <sv:value>superuser</sv:value>
      </sv:property>
      <sv:property sv:name="mgnl:lastmodified" sv:type="Date">
        <sv:value>2012-06-29T18:21:11.394+02:00</sv:value>
      </sv:property>
    </sv:node>
    <sv:node sv:name="0">
      <sv:property sv:name="jcr:primaryType" sv:type="Name">
        <sv:value>mgnl:component</sv:value>
      </sv:property>
      <sv:property sv:name="jcr:mixinTypes" sv:type="Name" sv:multiple="true">
        <sv:value>mix:lockable</sv:value>
      </sv:property>
      <sv:property sv:name="jcr:uuid" sv:type="String">
        <sv:value>f4ffef1a-439c-4686-bcee-aeea8ee2bdb4</sv:value>
      </sv:property>
      <sv:property sv:name="body" sv:type="String">
        <sv:value>&lt;p&gt;This is the sample component inside the&amp;nbsp;&lt;strong&gt;left column&lt;/strong&gt;&lt;/p&gt;</sv:value>
      </sv:property>
      <sv:property sv:name="jcr:createdBy" sv:type="String">
        <sv:value>admin</sv:value>
      </sv:property>
      <sv:node sv:name="MetaData">
        <sv:property sv:name="jcr:primaryType" sv:type="Name">
          <sv:value>mgnl:metaData</sv:value>
        </sv:property>
        <sv:property sv:name="jcr:createdBy" sv:type="String">
          <sv:value>admin</sv:value>
        </sv:property>
        <sv:property sv:name="mgnl:authorid" sv:type="String">
          <sv:value>superuser</sv:value>
        </sv:property>
        <sv:property sv:name="mgnl:creationdate" sv:type="Date">
          <sv:value>2012-06-29T18:19:23.123+02:00</sv:value>
        </sv:property>
        <sv:property sv:name="mgnl:lastmodified" sv:type="Date">
          <sv:value>2012-06-29T18:21:11.393+02:00</sv:value>
        </sv:property>
        <sv:property sv:name="mgnl:template" sv:type="String">
          <sv:value>blossomModuleSample:components/text</sv:value>
        </sv:property>
      </sv:node>
      <sv:node sv:name="body_files">
        <sv:property sv:name="jcr:primaryType" sv:type="Name">
          <sv:value>mgnl:contentNode</sv:value>
        </sv:property>
        <sv:property sv:name="jcr:mixinTypes" sv:type="Name" sv:multiple="true">
          <sv:value>mix:lockable</sv:value>
        </sv:property>
        <sv:property sv:name="jcr:uuid" sv:type="String">
          <sv:value>3ee7bd68-7811-4ffb-8411-6ad363c369fc</sv:value>
        </sv:property>
        <sv:property sv:name="jcr:createdBy" sv:type="String">
          <sv:value>admin</sv:value>
        </sv:property>
        <sv:node sv:name="MetaData">
          <sv:property sv:name="jcr:primaryType" sv:type="Name">
            <sv:value>mgnl:metaData</sv:value>
          </sv:property>
          <sv:property sv:name="jcr:createdBy" sv:type="String">
            <sv:value>admin</sv:value>
          </sv:property>
          <sv:property sv:name="mgnl:creationdate" sv:type="Date">
            <sv:value>2012-06-29T18:19:23.125+02:00</sv:value>
          </sv:property>
        </sv:node>
      </sv:node>
    </sv:node>
  </sv:node>
  <sv:node sv:name="right">
    <sv:property sv:name="jcr:primaryType" sv:type="Name">
      <sv:value>mgnl:area</sv:value>
    </sv:property>
    <sv:property sv:name="jcr:uuid" sv:type="String">
      <sv:value>624c6f2b-d228-4397-b8d6-a4144430faf1</sv:value>
    </sv:property>
    <sv:property sv:name="jcr:createdBy" sv:type="String">
      <sv:value>admin</sv:value>
    </sv:property>
    <sv:node sv:name="MetaData">
      <sv:property sv:name="jcr:primaryType" sv:type="Name">
        <sv:value>mgnl:metaData</sv:value>
      </sv:property>
      <sv:property sv:name="jcr:createdBy" sv:type="String">
        <sv:value>admin</sv:value>
      </sv:property>
      <sv:property sv:name="mgnl:authorid" sv:type="String">
        <sv:value>superuser</sv:value>
      </sv:property>
      <sv:property sv:name="mgnl:lastmodified" sv:type="Date">
        <sv:value>2012-06-29T18:21:00.647+02:00</sv:value>
      </sv:property>
    </sv:node>
    <sv:node sv:name="0">
      <sv:property sv:name="jcr:primaryType" sv:type="Name">
        <sv:value>mgnl:component</sv:value>
      </sv:property>
      <sv:property sv:name="jcr:mixinTypes" sv:type="Name" sv:multiple="true">
        <sv:value>mix:lockable</sv:value>
      </sv:property>
      <sv:property sv:name="jcr:uuid" sv:type="String">
        <sv:value>595ea4af-76ad-46fa-b28d-c139ba724a89</sv:value>
      </sv:property>
      <sv:property sv:name="body" sv:type="String">
        <sv:value>&lt;p&gt;This is the sample component inside the &lt;strong&gt;right column&lt;/strong&gt;&lt;/p&gt;</sv:value>
      </sv:property>
      <sv:property sv:name="jcr:createdBy" sv:type="String">
        <sv:value>admin</sv:value>
      </sv:property>
      <sv:node sv:name="MetaData">
        <sv:property sv:name="jcr:primaryType" sv:type="Name">
          <sv:value>mgnl:metaData</sv:value>
        </sv:property>
        <sv:property sv:name="jcr:createdBy" sv:type="String">
          <sv:value>admin</sv:value>
        </sv:property>
        <sv:property sv:name="mgnl:authorid" sv:type="String">
          <sv:value>superuser</sv:value>
        </sv:property>
        <sv:property sv:name="mgnl:creationdate" sv:type="Date">
          <sv:value>2012-06-29T18:05:25.506+02:00</sv:value>
        </sv:property>
        <sv:property sv:name="mgnl:lastmodified" sv:type="Date">
          <sv:value>2012-06-29T18:21:00.646+02:00</sv:value>
        </sv:property>
        <sv:property sv:name="mgnl:template" sv:type="String">
          <sv:value>blossomModuleSample:components/text</sv:value>
        </sv:property>
      </sv:node>
      <sv:node sv:name="body_files">
        <sv:property sv:name="jcr:primaryType" sv:type="Name">
          <sv:value>mgnl:contentNode</sv:value>
        </sv:property>
        <sv:property sv:name="jcr:mixinTypes" sv:type="Name" sv:multiple="true">
          <sv:value>mix:lockable</sv:value>
        </sv:property>
        <sv:property sv:name="jcr:uuid" sv:type="String">
          <sv:value>d55c3d2f-2478-4d6a-8bad-54c69100bfb5</sv:value>
        </sv:property>
        <sv:property sv:name="jcr:createdBy" sv:type="String">
          <sv:value>admin</sv:value>
        </sv:property>
        <sv:node sv:name="MetaData">
          <sv:property sv:name="jcr:primaryType" sv:type="Name">
            <sv:value>mgnl:metaData</sv:value>
          </sv:property>
          <sv:property sv:name="jcr:createdBy" sv:type="String">
            <sv:value>admin</sv:value>
          </sv:property>
          <sv:property sv:name="mgnl:creationdate" sv:type="Date">
            <sv:value>2012-06-29T18:05:25.508+02:00</sv:value>
          </sv:property>
        </sv:node>
      </sv:node>
    </sv:node>
  </sv:node>
  <sv:node sv:name="body_files">
    <sv:property sv:name="jcr:primaryType" sv:type="Name">
      <sv:value>mgnl:contentNode</sv:value>
    </sv:property>
    <sv:property sv:name="jcr:mixinTypes" sv:type="Name" sv:multiple="true">
      <sv:value>mix:lockable</sv:value>
    </sv:property>
    <sv:property sv:name="jcr:uuid" sv:type="String">
      <sv:value>fcc5832e-7d34-49e8-8e13-ffb42b68a86e</sv:value>
    </sv:property>
    <sv:property sv:name="jcr:createdBy" sv:type="String">
      <sv:value>admin</sv:value>
    </sv:property>
    <sv:node sv:name="MetaData">
      <sv:property sv:name="jcr:primaryType" sv:type="Name">
        <sv:value>mgnl:metaData</sv:value>
      </sv:property>
      <sv:property sv:name="jcr:createdBy" sv:type="String">
        <sv:value>admin</sv:value>
      </sv:property>
      <sv:property sv:name="mgnl:creationdate" sv:type="Date">
        <sv:value>2012-06-29T18:03:03.446+02:00</sv:value>
      </sv:property>
    </sv:node>
  </sv:node>
</sv:node>
